{
  "highways": {
    "PRK_PY_KS": {
      "name": "Pyongyang - Kaesong Expressway (Reunification Highway)",
      "coordinates": [
        [125.7625, 39.0392],
        [125.7400, 38.9500],
        [125.7200, 38.8300],
        [125.7000, 38.7100],
        [125.7100, 38.6000],
        [125.7300, 38.5000],
        [125.7500, 38.4000],
        [126.5600, 37.9712]
      ]
    },
    "PRK_PY_WS": {
      "name": "Pyongyang - Wonsan Expressway",
      "coordinates": [
        [125.7625, 39.0392],
        [125.8800, 39.0600],
        [126.0200, 39.0800],
        [126.1800, 39.0900],
        [126.3600, 39.1000],
        [126.5200, 39.1100],
        [126.6800, 39.1300],
        [126.8300, 39.1500],
        [127.0100, 39.1600],
        [127.4433, 39.1571]
      ]
    },
    "PRK_PY_NP": {
      "name": "Pyongyang - Nampo Expressway (Youth Hero Highway)",
      "coordinates": [
        [125.7625, 39.0392],
        [125.7000, 39.0200],
        [125.6200, 39.0000],
        [125.5200, 38.9800],
        [125.4200, 38.9600],
        [125.3200, 38.9400],
        [125.2100, 38.9200],
        [125.4078, 38.7369]
      ]
    }
  }
}
