{
  "highways": {
    "A1": {
      "name": "A1 Genf-Lausanne-Bern-Zürich-St. Gallen",
      "coordinates": [
        [6.15, 46.21], [6.25, 46.28], [6.35, 46.35], [6.45, 46.42],
        [6.55, 46.48], [6.63, 46.52], [6.72, 46.55], [6.82, 46.58],
        [6.92, 46.62], [7.02, 46.68], [7.12, 46.72], [7.22, 46.78],
        [7.32, 46.85], [7.42, 46.90], [7.45, 46.95], [7.50, 47.00],
        [7.55, 47.05], [7.62, 47.10], [7.70, 47.15], [7.78, 47.18],
        [7.88, 47.20], [7.98, 47.22], [8.08, 47.25], [8.18, 47.28],
        [8.28, 47.32], [8.38, 47.35], [8.48, 47.37], [8.55, 47.38],
        [8.65, 47.38], [8.75, 47.40], [8.85, 47.42], [8.95, 47.43],
        [9.05, 47.43], [9.15, 47.42], [9.25, 47.42], [9.38, 47.42]
      ]
    },
    "A2": {
      "name": "A2 Basel-Luzern-Gotthard-Chiasso",
      "coordinates": [
        [7.59, 47.56], [7.62, 47.50], [7.65, 47.45], [7.70, 47.40],
        [7.75, 47.35], [7.82, 47.30], [7.90, 47.25], [7.98, 47.20],
        [8.05, 47.15], [8.12, 47.10], [8.20, 47.05], [8.30, 47.05],
        [8.38, 47.00], [8.42, 46.95], [8.45, 46.88], [8.48, 46.82],
        [8.52, 46.75], [8.58, 46.68], [8.62, 46.62], [8.68, 46.55],
        [8.75, 46.48], [8.82, 46.42], [8.88, 46.35], [8.92, 46.28],
        [8.95, 46.22], [8.95, 46.15], [8.96, 46.08], [8.98, 46.00]
      ]
    },
    "A3": {
      "name": "A3 Zürich-Chur",
      "coordinates": [
        [8.52, 47.37], [8.62, 47.35], [8.72, 47.32], [8.82, 47.28],
        [8.88, 47.22], [8.92, 47.18], [8.98, 47.12], [9.05, 47.08],
        [9.12, 47.02], [9.18, 46.98], [9.25, 46.95], [9.32, 46.92],
        [9.40, 46.88], [9.48, 46.85], [9.53, 46.85]
      ]
    },
    "A3_Basel": {
      "name": "A3 Basel-Zürich",
      "coordinates": [
        [7.59, 47.56], [7.68, 47.55], [7.78, 47.52], [7.88, 47.50],
        [7.98, 47.48], [8.08, 47.47], [8.18, 47.45], [8.28, 47.42],
        [8.38, 47.40], [8.48, 47.38], [8.52, 47.37]
      ]
    },
    "A4": {
      "name": "A4 Zürich-Schaffhausen",
      "coordinates": [
        [8.52, 47.40], [8.55, 47.45], [8.58, 47.50], [8.60, 47.55],
        [8.62, 47.60], [8.63, 47.65], [8.64, 47.70]
      ]
    },
    "A5": {
      "name": "A5 Biel-Neuenburg-Yverdon",
      "coordinates": [
        [7.25, 47.14], [7.15, 47.10], [7.05, 47.05], [6.95, 47.00],
        [6.93, 46.95], [6.85, 46.90], [6.78, 46.85], [6.68, 46.80],
        [6.62, 46.78]
      ]
    },
    "A6": {
      "name": "A6 Bern-Thun-Spiez",
      "coordinates": [
        [7.45, 46.95], [7.48, 46.90], [7.52, 46.85], [7.58, 46.80],
        [7.62, 46.76], [7.65, 46.72], [7.68, 46.68]
      ]
    },
    "A8": {
      "name": "A8 Spiez-Interlaken",
      "coordinates": [
        [7.68, 46.68], [7.72, 46.68], [7.78, 46.68], [7.82, 46.69],
        [7.86, 46.69]
      ]
    },
    "A9": {
      "name": "A9 Lausanne-Sion-Brig",
      "coordinates": [
        [6.63, 46.52], [6.72, 46.48], [6.82, 46.45], [6.92, 46.42],
        [7.02, 46.38], [7.12, 46.35], [7.22, 46.32], [7.35, 46.28],
        [7.48, 46.25], [7.62, 46.22], [7.78, 46.22], [7.92, 46.25],
        [8.02, 46.30], [8.08, 46.32]
      ]
    },
    "A12": {
      "name": "A12 Bern-Fribourg",
      "coordinates": [
        [7.45, 46.95], [7.38, 46.92], [7.30, 46.88], [7.22, 46.85],
        [7.16, 46.81]
      ]
    },
    "A13": {
      "name": "A13 Chur-Bellinzona",
      "coordinates": [
        [9.53, 46.85], [9.48, 46.80], [9.42, 46.75], [9.35, 46.70],
        [9.28, 46.65], [9.22, 46.58], [9.18, 46.52], [9.15, 46.45],
        [9.12, 46.38], [9.08, 46.32], [9.05, 46.25], [9.02, 46.19]
      ]
    },
    "A14": {
      "name": "A14 Luzern-Zug",
      "coordinates": [
        [8.31, 47.05], [8.38, 47.08], [8.45, 47.10], [8.50, 47.12],
        [8.52, 47.15]
      ]
    }
  }
}